aas_pydantic/__init__.py
aas_pydantic/aas_model.py
aas_pydantic/convert_aas_instance.py
aas_pydantic/convert_aas_template.py
aas_pydantic/convert_pydantic_model.py
aas_pydantic/convert_pydantic_type.py
aas_pydantic/convert_util.py
aas_pydantic/util.py
aas_pydantic-0.1.3.dist-info/LICENSE
aas_pydantic-0.1.3.dist-info/METADATA
aas_pydantic-0.1.3.dist-info/WHEEL
aas_pydantic-0.1.3.dist-info/RECORD
