Metadata-Version: 2.1
Name: aas-pydantic
Version: 0.1.3
Summary: aas-pydantic is a package that combines the basyx python sdk for handling Asset Administration Shells (AAS) with pydantic Basemodels for fast and easy modeling and transformation of pydantic models and AAS.
Author: Sebastian Behrendt
Author-email: sebastianbehrendt97@gmail.com
Requires-Python: >=3.10,<4.0
Classifier: Programming Language :: Python :: 3
Classifier: Programming Language :: Python :: 3.10
Classifier: Programming Language :: Python :: 3.11
Requires-Dist: basyx-python-sdk (>=1.0.0,<2.0.0)
Requires-Dist: pydantic (>=2.10.1,<3.0.0)
Requires-Dist: stringcase (>=1.2.0,<2.0.0)
